{
  "course": {
    "id": "algebra-1",
    "title": "Algebra 1",
    "state": "Florida BEST",
    "platform": "Algebra OS",
    "version": "1.0.0"
  },
  "units": [
    {
      "id": "unit-1",
      "title": "Expressions, Equations, and Inequalities",
      "quarter": "Q1",
      "order": 1,
      "lessons": [
        {
          "id": "1.1",
          "title": "Solving One-Step Equations",
          "standard": "MA.912.AR.2.2",
          "objective": "Students will solve one-step linear equations using inverse operations.",
          "essentialQuestion": "How can inverse operations help solve equations?",
          "skills": [
            "identify the operation in an equation",
            "apply inverse operations",
            "solve one-step equations",
            "check solutions"
          ],
          "problemTypes": [
            "one_step_addition_equation",
            "one_step_subtraction_equation",
            "one_step_multiplication_equation",
            "one_step_division_equation"
          ],
          "dokLevels": [1, 2],
          "difficultyRange": {
            "min": 1,
            "max": 3
          },
          "realWorldRequired": true,
          "eocRigor": "foundational",
          "prerequisites": [],
          "unlockAfter": null
        },
                {
          "id": "1.2",
          "title": "Solving Multi-Step Equations",
          "standard": "MA.912.AR.2.2",
          "objective": "Students will solve multi-step linear equations using properties of equality.",
          "essentialQuestion": "How can multi-step equations be solved efficiently?",
          "skills": [
            "combine like terms",
            "use the distributive property",
            "isolate the variable",
            "check solutions"
          ],
          "problemTypes": [
            "multi_step_equation",
            "combine_like_terms_equation",
            "distributive_property_equation"
          ],
          "dokLevels": [1, 2, 3],
          "difficultyRange": {
            "min": 2,
            "max": 4
          },
          "realWorldRequired": true,
          "eocRigor": "medium",
          "prerequisites": ["1.1"],
          "unlockAfter": "1.1"
        },

        {
          "id": "1.3",
          "title": "Solving Equations with Variables on Both Sides",
          "standard": "MA.912.AR.2.2",
          "objective": "Students will solve linear equations that contain variables on both sides of the equation.",
          "essentialQuestion": "How can you solve equations when variables appear on both sides?",
          "skills": [
            "move variable terms",
            "move constant terms",
            "combine like terms",
            "isolate the variable",
            "verify solutions"
          ],
          "problemTypes": [
            "variables_both_sides"
          ],
          "dokLevels": [2, 3],
          "difficultyRange": {
            "min": 3,
            "max": 5
          },
          "realWorldRequired": true,
          "eocRigor": "medium",
          "prerequisites": ["1.2"],
          "unlockAfter": "1.2"
        }
      ]
    }
  ]
}
